Workbook

Sheet Сценарии
A1: Экономические варианты · 20 скважин · три цикла по каждому объекту
A2: Сценарии и суммы синтетические; агрегаты ниже не являются фактическим производственным эффектом.
A4: ID экономического варианта | B4: ID скважины | C4: Объект | D4: Дата оценки | E4: Цикл, № | F4: Сценарий | G4: Вариант мероприятия | H4: МРП до, сут. | I4: Прогноз МРП, сут. | J4: Доп. дни | K4: Дебит нефти, м³/сут | L4: Netback, руб./м³ | M4: Валовый эффект, руб. | N4: CAPEX, руб. | O4: OPEX, руб./год | P4: Чистый эффект, руб. | Q4: Выгода/затраты | R4: Окупаемость, мес.
A5: EC-TRN-01-C1-A | B5: TRN-01 | C5: Учебная скважина 01 · Авиловское учебное / скв. 101 / Бобриковский горизонт | D5: 45327 | E5: 1 | F5: Повтор метода | G5: Повторная корректировка: Ингибитор солеотложений | H5: 92 | I5: 117 | J5: =MAX(I5-H5,0) | K5: 24.4 | L5: 11500 | M5: =J5*K5*L5 | N5: 283500 | O5: 115000 | P5: =M5-N5-O5*J5/365 | Q5: =IFERROR(M5/(N5+O5*J5/365),0) | R5: =IFERROR(N5/((M5/MAX(1,J5)*365)-O5)*12,0)
A6: EC-TRN-01-C1-B | B6: TRN-01 | C6: Учебная скважина 01 · Авиловское учебное / скв. 101 / Бобриковский горизонт | D6: 45327 | E6: 1 | F6: Новый подбор | G6: Повторная корректировка: Ингибитор солеотложений · лабораторная корректировка | H6: 92 | I6: 147 | J6: =MAX(I6-H6,0) | K6: 24.4 | L6: 11500 | M6: =J6*K6*L6 | N6: 523500 | O6: 165000 | P6: =M6-N6-O6*J6/365 | Q6: =IFERROR(M6/(N6+O6*J6/365),0) | R6: =IFERROR(N6/((M6/MAX(1,J6)*365)-O6)*12,0)
A7: EC-TRN-01-C1-C | B7: TRN-01 | C7: Учебная скважина 01 · Авиловское учебное / скв. 101 / Бобриковский горизонт | D7: 45327 | E7: 1 | F7: Комплексная защита | G7: Комплекс: Повторная корректировка: Ингибитор солеотложений + мониторинг | H7: 92 | I7: 177 | J7: =MAX(I7-H7,0) | K7: 24.4 | L7: 11500 | M7: =J7*K7*L7 | N7: 763500 | O7: 235000 | P7: =M7-N7-O7*J7/365 | Q7: =IFERROR(M7/(N7+O7*J7/365),0) | R7: =IFERROR(N7/((M7/MAX(1,J7)*365)-O7)*12,0)
A8: EC-TRN-01-C2-A | B8: TRN-01 | C8: Учебная скважина 01 · Авиловское учебное / скв. 101 / Бобриковский горизонт | D8: 45855 | E8: 2 | F8: Повтор метода | G8: Фильтрация и контроль фракций | H8: 523 | I8: 565 | J8: =MAX(I8-H8,0) | K8: 24.4 | L8: 11500 | M8: =J8*K8*L8 | N8: 283500 | O8: 115000 | P8: =M8-N8-O8*J8/365 | Q8: =IFERROR(M8/(N8+O8*J8/365),0) | R8: =IFERROR(N8/((M8/MAX(1,J8)*365)-O8)*12,0)
A9: EC-TRN-01-C2-B | B9: TRN-01 | C9: Учебная скважина 01 · Авиловское учебное / скв. 101 / Бобриковский горизонт | D9: 45855 | E9: 2 | F9: Новый подбор | G9: Фильтрация и контроль фракций · лабораторная корректировка | H9: 523 | I9: 595 | J9: =MAX(I9-H9,0) | K9: 24.4 | L9: 11500 | M9: =J9*K9*L9 | N9: 523500 | O9: 165000 | P9: =M9-N9-O9*J9/365 | Q9: =IFERROR(M9/(N9+O9*J9/365),0) | R9: =IFERROR(N9/((M9/MAX(1,J9)*365)-O9)*12,0)
A10: EC-TRN-01-C2-C | B10: TRN-01 | C10: Учебная скважина 01 · Авиловское учебное / скв. 101 / Бобриковский горизонт | D10: 45855 | E10: 2 | F10: Комплексная защита | G10: Комплекс: Фильтрация и контроль фракций + мониторинг | H10: 523 | I10: 625 | J10: =MAX(I10-H10,0) | K10: 24.4 | L10: 11500 | M10: =J10*K10*L10 | N10: 763500 | O10: 235000 | P10: =M10-N10-O10*J10/365 | Q10: =IFERROR(M10/(N10+O10*J10/365),0) | R10: =IFERROR(N10/((M10/MAX(1,J10)*365)-O10)*12,0)
A11: EC-TRN-01-C3-A | B11: TRN-01 | C11: Учебная скважина 01 · Авиловское учебное / скв. 101 / Бобриковский горизонт | D11: 46082 | E11: 3 | F11: Повтор метода | G11: Биоцидная обработка + контроль | H11: 221 | I11: 280 | J11: =MAX(I11-H11,0) | K11: 24.4 | L11: 11500 | M11: =J11*K11*L11 | N11: 283500 | O11: 115000 | P11: =M11-N11-O11*J11/365 | Q11: =IFERROR(M11/(N11+O11*J11/365),0) | R11: =IFERROR(N11/((M11/MAX(1,J11)*365)-O11)*12,0)
A12: EC-TRN-01-C3-B | B12: TRN-01 | C12: Учебная скважина 01 · Авиловское учебное / скв. 101 / Бобриковский горизонт | D12: 46082 | E12: 3 | F12: Новый подбор | G12: Биоцидная обработка + контроль · лабораторная корректировка | H12: 221 | I12: 310 | J12: =MAX(I12-H12,0) | K12: 24.4 | L12: 11500 | M12: =J12*K12*L12 | N12: 523500 | O12: 165000 | P12: =M12-N12-O12*J12/365 | Q12: =IFERROR(M12/(N12+O12*J12/365),0) | R12: =IFERROR(N12/((M12/MAX(1,J12)*365)-O12)*12,0)
A13: EC-TRN-01-C3-C | B13: TRN-01 | C13: Учебная скважина 01 · Авиловское учебное / скв. 101 / Бобриковский горизонт | D13: 46082 | E13: 3 | F13: Комплексная защита | G13: Комплекс: Биоцидная обработка + контроль + мониторинг | H13: 221 | I13: 340 | J13: =MAX(I13-H13,0) | K13: 24.4 | L13: 11500 | M13: =J13*K13*L13 | N13: 763500 | O13: 235000 | P13: =M13-N13-O13*J13/365 | Q13: =IFERROR(M13/(N13+O13*J13/365),0) | R13: =IFERROR(N13/((M13/MAX(1,J13)*365)-O13)*12,0)
A14: EC-TRN-02-C1-A | B14: TRN-02 | C14: Учебная скважина 02 · Бешкульское учебное / скв. 102 / Батский III пласт | D14: 45425 | E14: 1 | F14: Повтор метода | G14: Подбор растворителя и профилактики | H14: 188 | I14: 226 | J14: =MAX(I14-H14,0) | K14: 27.7 | L14: 12800 | M14: =J14*K14*L14 | N14: 287000 | O14: 115000 | P14: =M14-N14-O14*J14/365 | Q14: =IFERROR(M14/(N14+O14*J14/365),0) | R14: =IFERROR(N14/((M14/MAX(1,J14)*365)-O14)*12,0)
A15: EC-TRN-02-C1-B | B15: TRN-02 | C15: Учебная скважина 02 · Бешкульское учебное / скв. 102 / Батский III пласт | D15: 45425 | E15: 1 | F15: Новый подбор | G15: Подбор растворителя и профилактики · лабораторная корректировка | H15: 188 | I15: 256 | J15: =MAX(I15-H15,0) | K15: 27.7 | L15: 12800 | M15: =J15*K15*L15 | N15: 527000 | O15: 165000 | P15: =M15-N15-O15*J15/365 | Q15: =IFERROR(M15/(N15+O15*J15/365),0) | R15: =IFERROR(N15/((M15/MAX(1,J15)*365)-O15)*12,0)
A16: EC-TRN-02-C1-C | B16: TRN-02 | C16: Учебная скважина 02 · Бешкульское учебное / скв. 102 / Батский III пласт | D16: 45425 | E16: 1 | F16: Комплексная защита | G16: Комплекс: Подбор растворителя и профилактики + мониторинг | H16: 188 | I16: 286 | J16: =MAX(I16-H16,0) | K16: 27.7 | L16: 12800 | M16: =J16*K16*L16 | N16: 767000 | O16: 235000 | P16: =M16-N16-O16*J16/365 | Q16: =IFERROR(M16/(N16+O16*J16/365),0) | R16: =IFERROR(N16/((M16/MAX(1,J16)*365)-O16)*12,0)
... A184: EC-TRN-20-C3-C | B184: TRN-20 | C184: Учебная скважина 20 · Юго-Западное учебное / скв. 120 / Турнейский горизонт | D184: 46295 | E184: 3 | F184: Комплексная защита | G184: Комплекс: Повторная корректировка: Подбор растворителя и профилактики + мониторинг | H184: 519 | I184: 610 | J184: =MAX(I184-H184,0) | K184: 33.2 | L184: 9800 | M184: =J184*K184*L184 | N184: 830000 | O184: 235000 | P184: =M184-N184-O184*J184/365 | Q184: =IFERROR(M184/(N184+O184*J184/365),0) | R184: =IFERROR(N184/((M184/MAX(1,J184)*365)-O184)*12,0)

Sheet Сводка экономики
A1: Экономическая сводка по сценариям
A2: Каждая строка сравнивает условный вариант для одного цикла. Суммарные значения — учебная выборка, не прогноз бюджета фонда.
A4: Сценарий | B4: Вариантов | C4: Доп. дни МРП | D4: Валовый эффект, руб. | E4: CAPEX, руб. | F4: OPEX с учетом доп. дней, руб. | G4: Чистый эффект, руб. | H4: Средний эффект на вариант, руб.
A5: Повтор метода | B5: =COUNTIF(Сценарии!$F$5:$F$184,A5) | C5: =SUMIF(Сценарии!$F$5:$F$184,A5,Сценарии!$J$5:$J$184) | D5: =SUMIF(Сценарии!$F$5:$F$184,A5,Сценарии!$M$5:$M$184) | E5: =SUMIF(Сценарии!$F$5:$F$184,A5,Сценарии!$N$5:$N$184) | F5: =SUMPRODUCT((Сценарии!$F$5:$F$184=A5)*Сценарии!$O$5:$O$184*Сценарии!$J$5:$J$184/365) | G5: =D5-E5-F5 | H5: =IFERROR(G5/B5,0)
A6: Новый подбор | B6: =COUNTIF(Сценарии!$F$5:$F$184,A6) | C6: =SUMIF(Сценарии!$F$5:$F$184,A6,Сценарии!$J$5:$J$184) | D6: =SUMIF(Сценарии!$F$5:$F$184,A6,Сценарии!$M$5:$M$184) | E6: =SUMIF(Сценарии!$F$5:$F$184,A6,Сценарии!$N$5:$N$184) | F6: =SUMPRODUCT((Сценарии!$F$5:$F$184=A6)*Сценарии!$O$5:$O$184*Сценарии!$J$5:$J$184/365) | G6: =D6-E6-F6 | H6: =IFERROR(G6/B6,0)
A7: Комплексная защита | B7: =COUNTIF(Сценарии!$F$5:$F$184,A7) | C7: =SUMIF(Сценарии!$F$5:$F$184,A7,Сценарии!$J$5:$J$184) | D7: =SUMIF(Сценарии!$F$5:$F$184,A7,Сценарии!$M$5:$M$184) | E7: =SUMIF(Сценарии!$F$5:$F$184,A7,Сценарии!$N$5:$N$184) | F7: =SUMPRODUCT((Сценарии!$F$5:$F$184=A7)*Сценарии!$O$5:$O$184*Сценарии!$J$5:$J$184/365) | G7: =D7-E7-F7 | H7: =IFERROR(G7/B7,0)
A9: Динамика экономических сценариев по году оценки
A11: Год | B11: Сценарий | C11: Вариантов | D11: Доп. дни МРП | E11: Валовый эффект, руб. | F11: CAPEX, руб. | G11: OPEX, руб. | H11: Чистый эффект, руб.
A12: 2024 | B12: Повтор метода | C12: =COUNTIFS(Сценарии!$F$5:$F$184,B12,Сценарии!$D$5:$D$184,">="&DATE(A12,1,1),Сценарии!$D$5:$D$184,"<="&DATE(A12,12,31)) | D12: =SUMIFS(Сценарии!$J$5:$J$184,Сценарии!$F$5:$F$184,B12,Сценарии!$D$5:$D$184,">="&DATE(A12,1,1),Сценарии!$D$5:$D$184,"<="&DATE(A12,12,31)) | E12: =SUMIFS(Сценарии!$M$5:$M$184,Сценарии!$F$5:$F$184,B12,Сценарии!$D$5:$D$184,">="&DATE(A12,1,1),Сценарии!$D$5:$D$184,"<="&DATE(A12,12,31)) | F12: =SUMIFS(Сценарии!$N$5:$N$184,Сценарии!$F$5:$F$184,B12,Сценарии!$D$5:$D$184,">="&DATE(A12,1,1),Сценарии!$D$5:$D$184,"<="&DATE(A12,12,31)) | G12: =SUMPRODUCT((Сценарии!$F$5:$F$184=B12)*(Сценарии!$D$5:$D$184>=DATE(A12,1,1))*(Сценарии!$D$5:$D$184<=DATE(A12,12,31))*Сценарии!$O$5:$O$184*Сценарии!$J$5:$J$184/365) | H12: =E12-F12-G12
A13: 2024 | B13: Новый подбор | C13: =COUNTIFS(Сценарии!$F$5:$F$184,B13,Сценарии!$D$5:$D$184,">="&DATE(A13,1,1),Сценарии!$D$5:$D$184,"<="&DATE(A13,12,31)) | D13: =SUMIFS(Сценарии!$J$5:$J$184,Сценарии!$F$5:$F$184,B13,Сценарии!$D$5:$D$184,">="&DATE(A13,1,1),Сценарии!$D$5:$D$184,"<="&DATE(A13,12,31)) | E13: =SUMIFS(Сценарии!$M$5:$M$184,Сценарии!$F$5:$F$184,B13,Сценарии!$D$5:$D$184,">="&DATE(A13,1,1),Сценарии!$D$5:$D$184,"<="&DATE(A13,12,31)) | F13: =SUMIFS(Сценарии!$N$5:$N$184,Сценарии!$F$5:$F$184,B13,Сценарии!$D$5:$D$184,">="&DATE(A13,1,1),Сценарии!$D$5:$D$184,"<="&DATE(A13,12,31)) | G13: =SUMPRODUCT((Сценарии!$F$5:$F$184=B13)*(Сценарии!$D$5:$D$184>=DATE(A13,1,1))*(Сценарии!$D$5:$D$184<=DATE(A13,12,31))*Сценарии!$O$5:$O$184*Сценарии!$J$5:$J$184/365) | H13: =E13-F13-G13
A14: 2024 | B14: Комплексная защита | C14: =COUNTIFS(Сценарии!$F$5:$F$184,B14,Сценарии!$D$5:$D$184,">="&DATE(A14,1,1),Сценарии!$D$5:$D$184,"<="&DATE(A14,12,31)) | D14: =SUMIFS(Сценарии!$J$5:$J$184,Сценарии!$F$5:$F$184,B14,Сценарии!$D$5:$D$184,">="&DATE(A14,1,1),Сценарии!$D$5:$D$184,"<="&DATE(A14,12,31)) | E14: =SUMIFS(Сценарии!$M$5:$M$184,Сценарии!$F$5:$F$184,B14,Сценарии!$D$5:$D$184,">="&DATE(A14,1,1),Сценарии!$D$5:$D$184,"<="&DATE(A14,12,31)) | F14: =SUMIFS(Сценарии!$N$5:$N$184,Сценарии!$F$5:$F$184,B14,Сценарии!$D$5:$D$184,">="&DATE(A14,1,1),Сценарии!$D$5:$D$184,"<="&DATE(A14,12,31)) | G14: =SUMPRODUCT((Сценарии!$F$5:$F$184=B14)*(Сценарии!$D$5:$D$184>=DATE(A14,1,1))*(Сценарии!$D$5:$D$184<=DATE(A14,12,31))*Сценарии!$O$5:$O$184*Сценарии!$J$5:$J$184/365) | H14: =E14-F14-G14
A15: 2025 | B15: Повтор метода | C15: =COUNTIFS(Сценарии!$F$5:$F$184,B15,Сценарии!$D$5:$D$184,">="&DATE(A15,1,1),Сценарии!$D$5:$D$184,"<="&DATE(A15,12,31)) | D15: =SUMIFS(Сценарии!$J$5:$J$184,Сценарии!$F$5:$F$184,B15,Сценарии!$D$5:$D$184,">="&DATE(A15,1,1),Сценарии!$D$5:$D$184,"<="&DATE(A15,12,31)) | E15: =SUMIFS(Сценарии!$M$5:$M$184,Сценарии!$F$5:$F$184,B15,Сценарии!$D$5:$D$184,">="&DATE(A15,1,1),Сценарии!$D$5:$D$184,"<="&DATE(A15,12,31)) | F15: =SUMIFS(Сценарии!$N$5:$N$184,Сценарии!$F$5:$F$184,B15,Сценарии!$D$5:$D$184,">="&DATE(A15,1,1),Сценарии!$D$5:$D$184,"<="&DATE(A15,12,31)) | G15: =SUMPRODUCT((Сценарии!$F$5:$F$184=B15)*(Сценарии!$D$5:$D$184>=DATE(A15,1,1))*(Сценарии!$D$5:$D$184<=DATE(A15,12,31))*Сценарии!$O$5:$O$184*Сценарии!$J$5:$J$184/365) | H15: =E15-F15-G15
A16: 2025 | B16: Новый подбор | C16: =COUNTIFS(Сценарии!$F$5:$F$184,B16,Сценарии!$D$5:$D$184,">="&DATE(A16,1,1),Сценарии!$D$5:$D$184,"<="&DATE(A16,12,31)) | D16: =SUMIFS(Сценарии!$J$5:$J$184,Сценарии!$F$5:$F$184,B16,Сценарии!$D$5:$D$184,">="&DATE(A16,1,1),Сценарии!$D$5:$D$184,"<="&DATE(A16,12,31)) | E16: =SUMIFS(Сценарии!$M$5:$M$184,Сценарии!$F$5:$F$184,B16,Сценарии!$D$5:$D$184,">="&DATE(A16,1,1),Сценарии!$D$5:$D$184,"<="&DATE(A16,12,31)) | F16: =SUMIFS(Сценарии!$N$5:$N$184,Сценарии!$F$5:$F$184,B16,Сценарии!$D$5:$D$184,">="&DATE(A16,1,1),Сценарии!$D$5:$D$184,"<="&DATE(A16,12,31)) | G16: =SUMPRODUCT((Сценарии!$F$5:$F$184=B16)*(Сценарии!$D$5:$D$184>=DATE(A16,1,1))*(Сценарии!$D$5:$D$184<=DATE(A16,12,31))*Сценарии!$O$5:$O$184*Сценарии!$J$5:$J$184/365) | H16: =E16-F16-G16
A17: 2025 | B17: Комплексная защита | C17: =COUNTIFS(Сценарии!$F$5:$F$184,B17,Сценарии!$D$5:$D$184,">="&DATE(A17,1,1),Сценарии!$D$5:$D$184,"<="&DATE(A17,12,31)) | D17: =SUMIFS(Сценарии!$J$5:$J$184,Сценарии!$F$5:$F$184,B17,Сценарии!$D$5:$D$184,">="&DATE(A17,1,1),Сценарии!$D$5:$D$184,"<="&DATE(A17,12,31)) | E17: =SUMIFS(Сценарии!$M$5:$M$184,Сценарии!$F$5:$F$184,B17,Сценарии!$D$5:$D$184,">="&DATE(A17,1,1),Сценарии!$D$5:$D$184,"<="&DATE(A17,12,31)) | F17: =SUMIFS(Сценарии!$N$5:$N$184,Сценарии!$F$5:$F$184,B17,Сценарии!$D$5:$D$184,">="&DATE(A17,1,1),Сценарии!$D$5:$D$184,"<="&DATE(A17,12,31)) | G17: =SUMPRODUCT((Сценарии!$F$5:$F$184=B17)*(Сценарии!$D$5:$D$184>=DATE(A17,1,1))*(Сценарии!$D$5:$D$184<=DATE(A17,12,31))*Сценарии!$O$5:$O$184*Сценарии!$J$5:$J$184/365) | H17: =E17-F17-G17
A18: 2026 | B18: Повтор метода | C18: =COUNTIFS(Сценарии!$F$5:$F$184,B18,Сценарии!$D$5:$D$184,">="&DATE(A18,1,1),Сценарии!$D$5:$D$184,"<="&DATE(A18,12,31)) | D18: =SUMIFS(Сценарии!$J$5:$J$184,Сценарии!$F$5:$F$184,B18,Сценарии!$D$5:$D$184,">="&DATE(A18,1,1),Сценарии!$D$5:$D$184,"<="&DATE(A18,12,31)) | E18: =SUMIFS(Сценарии!$M$5:$M$184,Сценарии!$F$5:$F$184,B18,Сценарии!$D$5:$D$184,">="&DATE(A18,1,1),Сценарии!$D$5:$D$184,"<="&DATE(A18,12,31)) | F18: =SUMIFS(Сценарии!$N$5:$N$184,Сценарии!$F$5:$F$184,B18,Сценарии!$D$5:$D$184,">="&DATE(A18,1,1),Сценарии!$D$5:$D$184,"<="&DATE(A18,12,31)) | G18: =SUMPRODUCT((Сценарии!$F$5:$F$184=B18)*(Сценарии!$D$5:$D$184>=DATE(A18,1,1))*(Сценарии!$D$5:$D$184<=DATE(A18,12,31))*Сценарии!$O$5:$O$184*Сценарии!$J$5:$J$184/365) | H18: =E18-F18-G18
A19: 2026 | B19: Новый подбор | C19: =COUNTIFS(Сценарии!$F$5:$F$184,B19,Сценарии!$D$5:$D$184,">="&DATE(A19,1,1),Сценарии!$D$5:$D$184,"<="&DATE(A19,12,31)) | D19: =SUMIFS(Сценарии!$J$5:$J$184,Сценарии!$F$5:$F$184,B19,Сценарии!$D$5:$D$184,">="&DATE(A19,1,1),Сценарии!$D$5:$D$184,"<="&DATE(A19,12,31)) | E19: =SUMIFS(Сценарии!$M$5:$M$184,Сценарии!$F$5:$F$184,B19,Сценарии!$D$5:$D$184,">="&DATE(A19,1,1),Сценарии!$D$5:$D$184,"<="&DATE(A19,12,31)) | F19: =SUMIFS(Сценарии!$N$5:$N$184,Сценарии!$F$5:$F$184,B19,Сценарии!$D$5:$D$184,">="&DATE(A19,1,1),Сценарии!$D$5:$D$184,"<="&DATE(A19,12,31)) | G19: =SUMPRODUCT((Сценарии!$F$5:$F$184=B19)*(Сценарии!$D$5:$D$184>=DATE(A19,1,1))*(Сценарии!$D$5:$D$184<=DATE(A19,12,31))*Сценарии!$O$5:$O$184*Сценарии!$J$5:$J$184/365) | H19: =E19-F19-G19
A20: 2026 | B20: Комплексная защита | C20: =COUNTIFS(Сценарии!$F$5:$F$184,B20,Сценарии!$D$5:$D$184,">="&DATE(A20,1,1),Сценарии!$D$5:$D$184,"<="&DATE(A20,12,31)) | D20: =SUMIFS(Сценарии!$J$5:$J$184,Сценарии!$F$5:$F$184,B20,Сценарии!$D$5:$D$184,">="&DATE(A20,1,1),Сценарии!$D$5:$D$184,"<="&DATE(A20,12,31)) | E20: =SUMIFS(Сценарии!$M$5:$M$184,Сценарии!$F$5:$F$184,B20,Сценарии!$D$5:$D$184,">="&DATE(A20,1,1),Сценарии!$D$5:$D$184,"<="&DATE(A20,12,31)) | F20: =SUMIFS(Сценарии!$N$5:$N$184,Сценарии!$F$5:$F$184,B20,Сценарии!$D$5:$D$184,">="&DATE(A20,1,1),Сценарии!$D$5:$D$184,"<="&DATE(A20,12,31)) | G20: =SUMPRODUCT((Сценарии!$F$5:$F$184=B20)*(Сценарии!$D$5:$D$184>=DATE(A20,1,1))*(Сценарии!$D$5:$D$184<=DATE(A20,12,31))*Сценарии!$O$5:$O$184*Сценарии!$J$5:$J$184/365) | H20: =E20-F20-G20
