Workbook

Sheet Параметры
A1: РОСА · БЛАНК ЭКОНОМИЧЕСКОЙ ОЦЕНКИ
A2: Заполните выделенные ячейки. Загружайте файл в разделе «6. Экономическая оценка» для выбранного объекта.
A3: Учебные значения и формулы не заменяют исходные данные и проверку экономиста. Реестр отказов в этот бланк не включается.
A4: Параметр | B4: Значение | C4: Единица | D4: Пояснение
A5: Объект | D5: Должен совпадать с объектом, закреплённым в РОСА; пустое значение означает текущий объект.
A6: Текущий МРП | C6: сут. | D6: Фактическая или принятая база для сравнения.
A7: МРП осторожный | C7: сут. | D7: Нижний сценарный прогноз.
A8: МРП центральный | C8: сут. | D8: Основной прогноз на выбранный горизонт.
A9: МРП благоприятный | C9: сут. | D9: Верхний сценарный прогноз.
A10: Выбранный сценарий | B10: Центральный | D10: Осторожный, Центральный или Благоприятный.
A11: Горизонт | B11: 36 | C11: мес. | D11: Целое число от 1 до 60 месяцев.
A12: Длительность ремонта | C12: сут. | D12: Средняя длительность одного ремонта.
A13: Стоимость ремонта | C13: руб. | D13: Стоимость одного ремонта.
A14: OPEX | C14: руб./год | D14: Эксплуатационные затраты выбранного варианта.
A15: Инфляция OPEX | B15: 0 | C15: %/год | D15: Годовой темп изменения эксплуатационных затрат.
A16: CAPEX | C16: руб. | D16: Разовые капитальные и материальные затраты.

Sheet Варианты
A1: ПАРАМЕТРЫ ПАРАЛЛЕЛЬНЫХ ЭКОНОМИЧЕСКИХ ВАРИАНТОВ
A2: Не меняйте состав методов в этой таблице. Названия и методы берутся из раздела 4; при загрузке строки применяются к вариантам по порядку.
A3: Пустые значения не заменяют показатели, уже сохранённые в выбранной схеме. Суммы — в рублях, МРП — в сутках.
A4: № | B4: Вариант | C4: Методы (справочно) | D4: МРП осторожный | E4: МРП центральный | F4: МРП благоприятный | G4: OPEX, руб./год | H4: CAPEX, руб.
A5: 1 | B5: Вариант 1
A6: 2 | B6: Вариант 2
A7: 3 | B7: Вариант 3

Sheet Сравнение
A1: СРАВНЕНИЕ ВАРИАНТОВ · ФОРМУЛЫ
A2: Результаты пересчитываются в Excel после заполнения листов «Параметры» и «Варианты». Суммарные значения не включают реестр отказов.
A4: Вариант | B4: МРП для расчёта, сут. | C4: Предотвращено ремонтов, шт./год | D4: Предотвращённый простой, сут./год | E4: Валовая выгода за горизонт, руб. | F4: OPEX за горизонт, руб. | G4: CAPEX, руб. | H4: Чистая выгода, руб. | I4: Выгода/затраты | J4: Окупаемость, мес.
A5: =Варианты!B5 | B5: =IF(Варианты!E5="",Параметры!$B$8,Варианты!E5) | C5: =IFERROR(MAX(0,365/Параметры!$B$6-365/B5),0) | D5: =C5*IF(Параметры!$B$12="",0,Параметры!$B$12) | E5: =C5*Параметры!$B$13*Параметры!$B$11/12 | F5: =SUMPRODUCT((ROW($1:$60)<=Параметры!$B$11)*IF(Варианты!G5="",Параметры!$B$14,Варианты!G5)/12*(1+Параметры!$B$15/100)^INT((ROW($1:$60)-1)/12)) | G5: =IF(Варианты!H5="",Параметры!$B$16,Варианты!H5) | H5: =E5-F5-G5 | I5: =IFERROR(E5/(F5+G5),0) | J5: =IFERROR(G5/(C5*Параметры!$B$13-F5*12/Параметры!$B$11)*12,"")
A6: =Варианты!B6 | B6: =IF(Варианты!E6="",Параметры!$B$8,Варианты!E6) | C6: =IFERROR(MAX(0,365/Параметры!$B$6-365/B6),0) | D6: =C6*IF(Параметры!$B$12="",0,Параметры!$B$12) | E6: =C6*Параметры!$B$13*Параметры!$B$11/12 | F6: =SUMPRODUCT((ROW($1:$60)<=Параметры!$B$11)*IF(Варианты!G6="",Параметры!$B$14,Варианты!G6)/12*(1+Параметры!$B$15/100)^INT((ROW($1:$60)-1)/12)) | G6: =IF(Варианты!H6="",Параметры!$B$16,Варианты!H6) | H6: =E6-F6-G6 | I6: =IFERROR(E6/(F6+G6),0) | J6: =IFERROR(G6/(C6*Параметры!$B$13-F6*12/Параметры!$B$11)*12,"")
A7: =Варианты!B7 | B7: =IF(Варианты!E7="",Параметры!$B$8,Варианты!E7) | C7: =IFERROR(MAX(0,365/Параметры!$B$6-365/B7),0) | D7: =C7*IF(Параметры!$B$12="",0,Параметры!$B$12) | E7: =C7*Параметры!$B$13*Параметры!$B$11/12 | F7: =SUMPRODUCT((ROW($1:$60)<=Параметры!$B$11)*IF(Варианты!G7="",Параметры!$B$14,Варианты!G7)/12*(1+Параметры!$B$15/100)^INT((ROW($1:$60)-1)/12)) | G7: =IF(Варианты!H7="",Параметры!$B$16,Варианты!H7) | H7: =E7-F7-G7 | I7: =IFERROR(E7/(F7+G7),0) | J7: =IFERROR(G7/(C7*Параметры!$B$13-F7*12/Параметры!$B$11)*12,"")
